{
    "CreatedDate": "2020-11-11T07:41:52.537",
    "CustomerKey": "223C5691-637E-401F-A7F0-B0624A665434",
    "Name": "subscriberspromotion",
    "Description": "",
    "IsSendable": "true",
    "IsTestable": "true",
    "SendableDataExtensionField": {
        "Name": "CustomerID"
    },
    "SendableSubscriberField": {
        "Name": "_SubscriberKey"
    },
    "RowBasedRetention": "false",
    "ResetRetentionPeriodOnImport": "false",
    "DeleteAtEndOfRetentionPeriod": "false",
    "RetainUntil": "",
    "Fields": [
        {
            "Name": "CustomerID",
            "Scale": "0",
            "DefaultValue": "",
            "MaxLength": "50",
            "IsRequired": "true",
            "IsPrimaryKey": "true",
            "FieldType": "Text"
        },
        {
            "Name": "Email Address",
            "Scale": "0",
            "DefaultValue": "",
            "MaxLength": "254",
            "IsRequired": "true",
            "IsPrimaryKey": "true",
            "FieldType": "EmailAddress"
        },
        {
            "Name": "FirstName",
            "Scale": "0",
            "DefaultValue": "Valued Customer",
            "MaxLength": "50",
            "IsRequired": "false",
            "IsPrimaryKey": "false",
            "FieldType": "Text"
        },
        {
            "Name": "LastName",
            "Scale": "0",
            "DefaultValue": "",
            "MaxLength": "50",
            "IsRequired": "false",
            "IsPrimaryKey": "false",
            "FieldType": "Text"
        },
        {
            "Name": "birthday",
            "DefaultValue": "GETDATE()",
            "IsRequired": "true",
            "IsPrimaryKey": "false",
            "FieldType": "Date"
        },
        {
            "Name": "application",
            "DefaultValue": "false",
            "IsRequired": "false",
            "IsPrimaryKey": "false",
            "FieldType": "Boolean"
        }
    ],
    "r__folder_ContentType": "dataextension",
    "r__folder_Path": "Data Extensions"
}
